{
    "courses": [
        {
            "id": 1001,
            "name": "Angular 10: Beginner",
            "desc": "Build professional, interactive apps with Angular, the most popular framework for building web.",
            "price": "FREE",
            "button_enabled": true
        },
        {
            "id": 1001,
            "name": "Angular 10: Beginner",
            "desc": "Build professional, interactive apps with Angular, the most popular framework for building web.",
            "price": "FREE",
            "button_enabled": true
        },
        {
            "id": 1001,
            "name": "Angular 10: Beginner",
            "desc": "Build professional, interactive apps with Angular, the most popular framework for building web.",
            "price": "FREE",
            "button_enabled": true
        },
        {
            "id": 1001,
            "name": "Angular 10: Beginner",
            "desc": "Build professional, interactive apps with Angular, the most popular framework for building web.",
            "price": "FREE",
            "button_enabled": true
        }
    ] 
}